calibreweb/__init__.py
calibreweb/__main__.py
calibreweb/optional-requirements.txt
calibreweb/requirements.txt
calibreweb/cps/.HOMEDIR
calibreweb/cps/MyLoginManager.py
calibreweb/cps/__init__.py
calibreweb/cps/about.py
calibreweb/cps/admin.py
calibreweb/cps/audio.py
calibreweb/cps/basic.py
calibreweb/cps/cache_buster.py
calibreweb/cps/clean_html.py
calibreweb/cps/cli.py
calibreweb/cps/comic.py
calibreweb/cps/config_sql.py
calibreweb/cps/constants.py
calibreweb/cps/converter.py
calibreweb/cps/cover.py
calibreweb/cps/cw_babel.py
calibreweb/cps/db.py
calibreweb/cps/debug_info.py
calibreweb/cps/dep_check.py
calibreweb/cps/editbooks.py
calibreweb/cps/embed_helper.py
calibreweb/cps/epub.py
calibreweb/cps/epub_helper.py
calibreweb/cps/error_handler.py
calibreweb/cps/fb2.py
calibreweb/cps/file_helper.py
calibreweb/cps/fs.py
calibreweb/cps/gdrive.py
calibreweb/cps/gdriveutils.py
calibreweb/cps/gevent_wsgi.py
calibreweb/cps/helper.py
calibreweb/cps/isoLanguages.py
calibreweb/cps/iso_language_names.py
calibreweb/cps/jinjia.py
calibreweb/cps/kobo.py
calibreweb/cps/kobo_auth.py
calibreweb/cps/kobo_sync_status.py
calibreweb/cps/logger.py
calibreweb/cps/main.py
calibreweb/cps/oauth.py
calibreweb/cps/oauth_bb.py
calibreweb/cps/opds.py
calibreweb/cps/pagination.py
calibreweb/cps/redirect.py
calibreweb/cps/remotelogin.py
calibreweb/cps/render_template.py
calibreweb/cps/reverseproxy.py
calibreweb/cps/schedule.py
calibreweb/cps/search.py
calibreweb/cps/search_metadata.py
calibreweb/cps/server.py
calibreweb/cps/shelf.py
calibreweb/cps/string_helper.py
calibreweb/cps/subproc_wrapper.py
calibreweb/cps/tasks_status.py
calibreweb/cps/tornado_wsgi.py
calibreweb/cps/ub.py
calibreweb/cps/updater.py
calibreweb/cps/uploader.py
calibreweb/cps/usermanagement.py
calibreweb/cps/web.py
calibreweb/cps/cw_advocate/__init__.py
calibreweb/cps/cw_advocate/adapters.py
calibreweb/cps/cw_advocate/addrvalidator.py
calibreweb/cps/cw_advocate/api.py
calibreweb/cps/cw_advocate/connection.py
calibreweb-0.6.25.dist-info/licenses/LICENSE
calibreweb-0.6.25.dist-info/METADATA
calibreweb-0.6.25.dist-info/WHEEL
calibreweb-0.6.25.dist-info/entry_points.txt
calibreweb-0.6.25.dist-info/top_level.txt
calibreweb-0.6.25.dist-info/RECORD
