Metadata-Version: 2.4
Name: calibreweb
Version: 0.6.25
Summary: Web app for browsing, reading and downloading eBooks stored in a Calibre database.
Author-email: "@OzzieIsaacs" <Ozzie.Fernandez.Isaacs@googlemail.com>
Maintainer: @OzzieIsaacs
License: GPLv3+
Project-URL: Homepage, https://github.com/janeczku/calibre-web
Project-URL: Bug Tracker, https://github.com/janeczku/calibre-web/issues
Project-URL: Release Management, https://github.com/janeczku/calibre-web/releases
Project-URL: Documentation, https://github.com/janeczku/calibre-web/wiki
Project-URL: Source Code, https://github.com/janeczku/calibre-web
Keywords: calibre,calibre-web,library
Classifier: Development Status :: 5 - Production/Stable
Classifier: License :: OSI Approved :: GNU Affero General Public License v3
Classifier: Programming Language :: Python :: 3
Classifier: Programming Language :: Python :: 3.8
Classifier: Programming Language :: Python :: 3.9
Classifier: Programming Language :: Python :: 3.10
Classifier: Programming Language :: Python :: 3.11
Classifier: Programming Language :: Python :: 3.12
Classifier: Programming Language :: Python :: 3.13
Classifier: Operating System :: OS Independent
Requires-Python: >=3.6
License-File: LICENSE
Requires-Dist: APScheduler<3.12.0,>=3.6.3
Requires-Dist: Babel<3.0,>=1.3
Requires-Dist: Flask-Babel<4.1.0,>=3.0.0
Requires-Dist: Flask-Principal<0.5.1,>=0.3.2
Requires-Dist: Flask<3.2.0,>=1.0.2
Requires-Dist: iso-639<0.5.0,>=0.4.5; python_version < "3.12"
Requires-Dist: pycountry<25.0.0,>=20.0.0; python_version >= "3.12"
Requires-Dist: PyPDF<5.5.0,>=3.15.6
Requires-Dist: pytz>=2016.10
Requires-Dist: requests<2.33.0,>=2.32.0
Requires-Dist: SQLAlchemy<2.1.0,>=1.3.0
Requires-Dist: tornado<6.6,>=6.4.2
Requires-Dist: Wand<0.7.0,>=0.4.4
Requires-Dist: unidecode<1.4.0,>=0.04.19
Requires-Dist: lxml<5.4.0,>=4.9.1
Requires-Dist: flask-wtf<1.3.0,>=0.14.2
Requires-Dist: chardet<5.3.0,>=3.0.0
Requires-Dist: netifaces-plus<0.13.0,>=0.12.0
Requires-Dist: urllib3<3.0,>=1.22
Requires-Dist: Flask-Limiter<3.13.0,>=2.3.0
Requires-Dist: regex<2025.3.20,>=2022.3.2
Requires-Dist: bleach<6.3.0,>=6.0.0
Requires-Dist: python-magic<0.5.0,>=0.4.27
Requires-Dist: python-magic-bin<0.5.0,>=0.4.0; sys_platform == "win32"
Requires-Dist: flask-httpAuth<5.0.0,>=4.4.0
Requires-Dist: cryptography<45.0.0,>=39.0.0
Provides-Extra: gdrive
Requires-Dist: google-api-python-client<2.200.0,>=1.7.11; extra == "gdrive"
Requires-Dist: gevent<24.12.0,>20.6.0; extra == "gdrive"
Requires-Dist: greenlet<3.2.0,>=0.4.17; extra == "gdrive"
Requires-Dist: httplib2<0.23.0,>=0.9.2; extra == "gdrive"
Requires-Dist: oauth2client<4.1.4,>=4.0.0; extra == "gdrive"
Requires-Dist: uritemplate<4.2.0,>=3.0.0; extra == "gdrive"
Requires-Dist: pyasn1-modules<0.7.0,>=0.0.8; extra == "gdrive"
Requires-Dist: pyasn1<0.7.0,>=0.1.9; extra == "gdrive"
Requires-Dist: PyDrive2<1.22.0,>=1.3.1; extra == "gdrive"
Requires-Dist: PyYAML<6.1,>=3.12; extra == "gdrive"
Requires-Dist: rsa<4.10.0,>=3.4.2; extra == "gdrive"
Provides-Extra: gmail
Requires-Dist: google-auth-oauthlib<1.3.0,>=0.4.3; extra == "gmail"
Requires-Dist: google-api-python-client<2.200.0,>=1.7.11; extra == "gmail"
Provides-Extra: goodreads
Requires-Dist: goodreads<0.4.0,>=0.3.2; extra == "goodreads"
Requires-Dist: python-Levenshtein<0.28.0,>=0.12.0; extra == "goodreads"
Provides-Extra: ldap
Requires-Dist: python-ldap<3.5.0,>=3.0.0; extra == "ldap"
Requires-Dist: Flask-SimpleLDAP<2.1.0,>=1.4.0; extra == "ldap"
Provides-Extra: oauth
Requires-Dist: Flask-Dance<7.2.0,>=2.0.0; extra == "oauth"
Requires-Dist: SQLAlchemy-Utils<0.42.0,>=0.33.5; extra == "oauth"
Provides-Extra: metadata
Requires-Dist: rarfile<5.0,>=3.2; extra == "metadata"
Requires-Dist: scholarly<1.8,>=1.2.0; extra == "metadata"
Requires-Dist: markdown2<2.6.0,>=2.0.0; extra == "metadata"
Requires-Dist: html2text<2025.2.26,>=2020.1.16; extra == "metadata"
Requires-Dist: python-dateutil<2.10.0,>=2.1; extra == "metadata"
Requires-Dist: beautifulsoup4<4.14.0,>=4.0.1; extra == "metadata"
Requires-Dist: faust-cchardet<2.1.20,>=2.1.18; extra == "metadata"
Requires-Dist: py7zr<0.21.0,>=0.15.0; extra == "metadata"
Requires-Dist: mutagen<1.50.0,>=1.40.0; extra == "metadata"
Requires-Dist: pycountry<25.0.0,>=20.0.0; extra == "metadata"
Provides-Extra: comics
Requires-Dist: natsort<8.5.0,>=2.2.0; extra == "comics"
Requires-Dist: comicapi<3.3.0,>=2.2.0; extra == "comics"
Provides-Extra: kobo
Requires-Dist: jsonschema<4.24.0,>=3.2.0; extra == "kobo"
Dynamic: license-file
